pybullet_envs_gymnasium/__init__.py
pybullet_envs_gymnasium/env_bases.py
pybullet_envs_gymnasium/gym_locomotion_envs.py
pybullet_envs_gymnasium/gym_manipulator_envs.py
pybullet_envs_gymnasium/gym_pendulum_envs.py
pybullet_envs_gymnasium/py.typed
pybullet_envs_gymnasium/robot_bases.py
pybullet_envs_gymnasium/robot_locomotors.py
pybullet_envs_gymnasium/robot_manipulators.py
pybullet_envs_gymnasium/robot_pendula.py
pybullet_envs_gymnasium/scene_abstract.py
pybullet_envs_gymnasium/scene_stadium.py
pybullet_envs_gymnasium/version.txt
pybullet_envs_gymnasium-0.6.0.dist-info/LICENSE
pybullet_envs_gymnasium-0.6.0.dist-info/METADATA
pybullet_envs_gymnasium-0.6.0.dist-info/WHEEL
pybullet_envs_gymnasium-0.6.0.dist-info/top_level.txt
pybullet_envs_gymnasium-0.6.0.dist-info/RECORD
