Metadata-Version: 2.2
Name: pybullet_envs_gymnasium
Version: 0.6.0
Summary: Gymnasium port of pybullet envs
Home-page: https://github.com/araffin/pybullet_envs_gymnasium
Author: Antonin Raffin
Author-email: antonin.raffin@dlr.de
License: zlib
Project-URL: Code, https://github.com/araffin/pybullet_envs_gymnasium
Project-URL: Original repo, https://github.com/bulletphysics/bullet3
Keywords: reinforcement-learning-algorithms reinforcement-learning machine-learning gymnasium gym openai stable baselines toolbox python data-science
Classifier: Programming Language :: Python :: 3
Classifier: Programming Language :: Python :: 3.9
Classifier: Programming Language :: Python :: 3.10
Classifier: Programming Language :: Python :: 3.11
Classifier: Programming Language :: Python :: 3.12
Requires-Python: >=3.9
License-File: LICENSE
Requires-Dist: pybullet>=3.2.5
Requires-Dist: gymnasium<2.0,>=0.29.1
Dynamic: author
Dynamic: author-email
Dynamic: classifier
Dynamic: description
Dynamic: description-content-type
Dynamic: home-page
Dynamic: keywords
Dynamic: license
Dynamic: project-url
Dynamic: requires-dist
Dynamic: requires-python
Dynamic: summary
